setup.py
wood_nester.py
wood_nester.egg-info/PKG-INFO
wood_nester.egg-info/SOURCES.txt
wood_nester.egg-info/dependency_links.txt
wood_nester.egg-info/top_level.txt