Metadata-Version: 2.1
Name: wood-nester
Version: 1.3.0
Summary: Simple printer of nested lists
Home-page: https://www.booksaround.net
Author: wood
Author-email: lezvinskyi@gmail.com
License: UNKNOWN
Platform: UNKNOWN
